setup.py
pyscores/__init__.py
pyscores/api_wrapper.py
pyscores/cli.py
pyscores/config.py
pyscores.egg-info/PKG-INFO
pyscores.egg-info/SOURCES.txt
pyscores.egg-info/dependency_links.txt
pyscores.egg-info/entry_points.txt
pyscores.egg-info/requires.txt
pyscores.egg-info/top_level.txt