Metadata-Version: 1.0
Name: pyscores
Version: 0.2
Summary: Football (soccer) scores in your command line
Home-page: https://github.com/conormag94/pyscores
Author: Conor Maguire
Author-email: conormag94@gmail.com
License: MIT
Platform: UNKNOWN
